neurapolis_retriever/__init__.py
neurapolis_retriever/config.py
neurapolis_retriever/edges/__init__.py
neurapolis_retriever/edges/after_cleaner_continute_to_relevance_graders_edge.py
neurapolis_retriever/edges/after_planner_continue_to_retrievers_edge.py
neurapolis_retriever/edges/after_sub_cleaner_continue_to_sub_relevance_graders_edge.py
neurapolis_retriever/edges/after_sub_planner_continue_to_sub_retrievers_edge.py
neurapolis_retriever/graph.py
neurapolis_retriever/neurapolis_retriever.py
neurapolis_retriever/nodes/__init__.py
neurapolis_retriever/nodes/cleaner_node.py
neurapolis_retriever/nodes/new_planner.py
neurapolis_retriever/nodes/planner_node.py
neurapolis_retriever/nodes/related_data_gatherer_node.py
neurapolis_retriever/nodes/relevance_grader_node.py
neurapolis_retriever/nodes/retriever_node.py
neurapolis_retriever/nodes/sub_planner_node.py
neurapolis_retriever/retriever_config.py
neurapolis_retriever/services/__init__.py
neurapolis_retriever/state/__init__.py
neurapolis_retriever/state/grading.py
neurapolis_retriever/state/hit.py
neurapolis_retriever/state/hit_step.py
neurapolis_retriever/state/related_data_state.py
neurapolis_retriever/state/search.py
neurapolis_retriever/state/search_step.py
neurapolis_retriever/state/search_type.py
neurapolis_retriever/state/state.py
neurapolis_retriever/utilities/__init__.py
neurapolis_retriever/utilities/generate_grading_llm_data_model.py
neurapolis_retriever/utilities/generate_llm_context_metadata.py
neurapolis_retriever-0.1.1.dist-info/METADATA
neurapolis_retriever-0.1.1.dist-info/WHEEL
neurapolis_retriever-0.1.1.dist-info/RECORD
